LICENSE
MANIFEST.in
README.md
setup.cfg
setup.py
limix_genetics/__init__.py
limix_genetics/_colors.py
limix_genetics/_config.py
limix_genetics/_core.py
limix_genetics/_mvnorm.py
limix_genetics/_powerplot.py
limix_genetics/_pvalues.py
limix_genetics/_qqplot.py
limix_genetics.egg-info/PKG-INFO
limix_genetics.egg-info/SOURCES.txt
limix_genetics.egg-info/dependency_links.txt
limix_genetics.egg-info/requires.txt
limix_genetics.egg-info/top_level.txt
limix_genetics.egg-info/zip-safe
limix_genetics/test/test_maf.py
limix_genetics/test/test_mvnorm.py