Metadata-Version: 1.1
Name: limix-genetics
Version: 0.1.6
Summary: Genetic-related tools for Limix.
Home-page: https://github.com/glimix/limix-genetics
Author: Limix Developers
Author-email: horta@ebi.ac.uk
License: MIT
Platform: UNKNOWN
Classifier: Development Status :: 5 - Production/Stable
Classifier: License :: OSI Approved :: MIT License
Classifier: Operating System :: OS Independent
